team4958_customs/__init__.py
team4958_customs/tools/__init__.py
team4958_customs/tools/asyncs.py
team4958_customs/tools/sql.py
team4958_customs/utilities/__init__.py
team4958_customs/utilities/assets/__init__.py
team4958_customs/utilities/assets/builder_presets.py
team4958_customs/utilities/common.py
team4958_customs/utilities/project_builder.py
team4958_customs/utils.py
team4958_customs-0.2.5.dist-info/LICENSE
team4958_customs-0.2.5.dist-info/METADATA
team4958_customs-0.2.5.dist-info/WHEEL
team4958_customs-0.2.5.dist-info/RECORD
