Metadata-Version: 2.1
Name: team4958-customs
Version: 0.2.5
Summary: some life-simplifying python tools for some lazy devs from some lazy devs
License: MIT
Author: arti404
Author-email: 113468982+arti404@users.noreply.github.com
Requires-Python: >=3.8,<4.0
Classifier: License :: OSI Approved :: MIT License
Classifier: Programming Language :: Python :: 3
Classifier: Programming Language :: Python :: 3.8
Classifier: Programming Language :: Python :: 3.9
Classifier: Programming Language :: Python :: 3.10
Classifier: Programming Language :: Python :: 3.11
Requires-Dist: asyncio (>=3.4.3,<4.0.0)
Requires-Dist: disnake (>=2.8.1,<3.0.0)
Requires-Dist: mysql-connector-python (>=8.1.0,<9.0.0)
